setup.py
Estadistica_Pesca.egg-info/PKG-INFO
Estadistica_Pesca.egg-info/SOURCES.txt
Estadistica_Pesca.egg-info/dependency_links.txt
Estadistica_Pesca.egg-info/top_level.txt
estadistica/__init__.py
estadistica/servicios.py
estadistica/settings.py