Metadata-Version: 1.0
Name: Estadistica-Pesca
Version: 1.0.0
Summary: Paquete de estadistica de pesca
Home-page: UNKNOWN
Author: SIOP
Author-email: yaramendia@inidep.edu.ar
License: UNKNOWN
Platform: UNKNOWN
